pyhmsa/__init__.py
pyhmsa/_version.py
pyhmsa/datafile.py
pyhmsa/test_datafile.py
pyhmsa/fileformat/__init__.py
pyhmsa/fileformat/datafile.py
pyhmsa/fileformat/test_datafile.py
pyhmsa/fileformat/common/__init__.py
pyhmsa/fileformat/common/emsa.py
pyhmsa/fileformat/common/test_esma.py
pyhmsa/fileformat/exporter/__init__.py
pyhmsa/fileformat/exporter/emsa.py
pyhmsa/fileformat/exporter/exporter.py
pyhmsa/fileformat/exporter/raw.py
pyhmsa/fileformat/exporter/test_emsa.py
pyhmsa/fileformat/exporter/test_exporter.py
pyhmsa/fileformat/exporter/test_raw.py
pyhmsa/fileformat/importer/__init__.py
pyhmsa/fileformat/importer/emsa.py
pyhmsa/fileformat/importer/importer.py
pyhmsa/fileformat/importer/raw.py
pyhmsa/fileformat/importer/test_emsa.py
pyhmsa/fileformat/importer/test_importer.py
pyhmsa/fileformat/importer/test_raw.py
pyhmsa/fileformat/xmlhandler/__init__.py
pyhmsa/fileformat/xmlhandler/header.py
pyhmsa/fileformat/xmlhandler/test_header.py
pyhmsa/fileformat/xmlhandler/test_xmlhandler.py
pyhmsa/fileformat/xmlhandler/xmlhandler.py
pyhmsa/fileformat/xmlhandler/condition/__init__.py
pyhmsa/fileformat/xmlhandler/condition/acquisition.py
pyhmsa/fileformat/xmlhandler/condition/calibration.py
pyhmsa/fileformat/xmlhandler/condition/composition.py
pyhmsa/fileformat/xmlhandler/condition/condition.py
pyhmsa/fileformat/xmlhandler/condition/detector.py
pyhmsa/fileformat/xmlhandler/condition/elementalid.py
pyhmsa/fileformat/xmlhandler/condition/instrument.py
pyhmsa/fileformat/xmlhandler/condition/probe.py
pyhmsa/fileformat/xmlhandler/condition/region.py
pyhmsa/fileformat/xmlhandler/condition/specimen.py
pyhmsa/fileformat/xmlhandler/condition/specimenposition.py
pyhmsa/fileformat/xmlhandler/condition/test_acquisition.py
pyhmsa/fileformat/xmlhandler/condition/test_calibration.py
pyhmsa/fileformat/xmlhandler/condition/test_composition.py
pyhmsa/fileformat/xmlhandler/condition/test_detector.py
pyhmsa/fileformat/xmlhandler/condition/test_elementalid.py
pyHMSA-0.2.0.dist-info/LICENSE
pyHMSA-0.2.0.dist-info/METADATA
pyHMSA-0.2.0.dist-info/WHEEL
pyHMSA-0.2.0.dist-info/entry_points.txt
pyHMSA-0.2.0.dist-info/top_level.txt
pyHMSA-0.2.0.dist-info/RECORD
