Metadata-Version: 2.1
Name: pyHMSA
Version: 0.2.0
Summary: Python implementation of the MSA / MAS / AMAS Hyper-Dimensional Data File specification
Home-page: http://pyhmsa.readthedocs.org
Author: Philippe Pinard
Author-email: philippe.pinard@gmail.com
Maintainer: Philippe Pinard
Maintainer-email: philippe.pinard@gmail.com
License: MIT
Keywords: microscopy microanalysis hmsa file format
Platform: UNKNOWN
Classifier: Development Status :: 4 - Beta
Classifier: Intended Audience :: Developers
Classifier: Intended Audience :: Science/Research
Classifier: Operating System :: OS Independent
Classifier: License :: OSI Approved :: MIT License
Classifier: Programming Language :: Python :: 3
Classifier: Programming Language :: Python :: 3.3
Classifier: Programming Language :: Python :: 3.4
Classifier: Topic :: Scientific/Engineering :: Physics
Requires-Dist: numpy
Requires-Dist: six
Provides-Extra: develop
Requires-Dist: pillow ; extra == 'develop'
Requires-Dist: nose ; extra == 'develop'
Requires-Dist: coverage ; extra == 'develop'
